diffusion623/__init__.py
diffusion623/trainer.py
diffusion623/unet.py
diffusion623/utils.py
diffusion623-0.1.4.dist-info/LICENSE
diffusion623-0.1.4.dist-info/METADATA
diffusion623-0.1.4.dist-info/WHEEL
diffusion623-0.1.4.dist-info/top_level.txt
diffusion623-0.1.4.dist-info/RECORD
